arc2control/__init__.py
arc2control/__main__.py
arc2control/arc2config.py
arc2control/constants.py
arc2control/fwutils.py
arc2control/graphics/__init__.py
arc2control/graphics/action-cancel.png
arc2control/graphics/action-delete.png
arc2control/graphics/action-download.png
arc2control/graphics/action-exit.png
arc2control/graphics/action-fw-manager.png
arc2control/graphics/action-new-dataset.png
arc2control/graphics/action-open.png
arc2control/graphics/action-refresh.png
arc2control/graphics/action-save-as.png
arc2control/graphics/action-save.png
arc2control/graphics/arc2-logo.svg
arc2control/graphics/drive-error-small.png
arc2control/graphics/splash.svg
arc2control/h5utils.py
arc2control/main.py
arc2control/mapper.py
arc2control/mappings/bnc6.toml
arc2control/mappings/probecard32.toml
arc2control/mappings/resarray32.toml
arc2control/mappings/sa-probecard32.toml
arc2control/mappings/sa-standard32.toml
arc2control/mappings/standard32.toml
arc2control/modules/__init__.py
arc2control/modules/autoformer/__init__.py
arc2control/modules/autoformer/af_display_widget.py
arc2control/modules/autoformer/autoformer.py
arc2control/modules/autoformer/uis/autoformer.ui
arc2control/modules/base.py
arc2control/modules/curvetracer/__init__.py
arc2control/modules/curvetracer/ct_display_widget.py
arc2control/modules/curvetracer/curvetracer.py
arc2control/modules/curvetracer/uis/curvetracer.ui
arc2control/modules/retention/__init__.py
arc2control/modules/retention/ret_display_widget.py
arc2control/modules/retention/retention.py
arc2control/signals.py
arc2control/version.py
arc2control/widgets/__init__.py
arc2control/widgets/about_dialog.py
arc2control/widgets/app.py
arc2control/widgets/arc2connection_widget.py
arc2control/widgets/collapsibletree_widget.py
arc2control/widgets/common.py
arc2control/widgets/crossbar_widget.py
arc2control/widgets/crossbarconfig_dialog.py
arc2control/widgets/datasettable_widget.py
arc2control/widgets/device_explorer_widget.py
arc2control-0.2.0.dist-info/LICENSE
arc2control-0.2.0.dist-info/METADATA
arc2control-0.2.0.dist-info/WHEEL
arc2control-0.2.0.dist-info/RECORD
