Metadata-Version: 2.3
Name: arc2control
Version: 0.2.0
Summary: ArC TWO Control Panel
Author: Spyros Stathopoulos
Author-email: devel@arc-instruments.co.uk
Requires-Python: >=3.10
Classifier: Development Status :: 3 - Alpha
Classifier: Intended Audience :: Science/Research
Classifier: Topic :: Scientific/Engineering
Classifier: License :: OSI Approved :: GNU General Public License v3 or later (GPLv3+)
Classifier: Operating System :: Microsoft :: Windows :: Windows 8
Classifier: Operating System :: Microsoft :: Windows :: Windows 8.1
Classifier: Operating System :: Microsoft :: Windows :: Windows 10
Classifier: Operating System :: POSIX :: Linux
Classifier: Programming Language :: Python :: 3 :: Only
Classifier: Programming Language :: Python :: 3.10
Classifier: Programming Language :: Python :: 3.11
Classifier: Programming Language :: Python :: 3.12
Classifier: Programming Language :: Python :: 3.13
Requires-Dist: PyQt6 (>=6.1)
Requires-Dist: cryptography (>=3.3.0)
Requires-Dist: h5py (>=3.0)
Requires-Dist: numpy (>=1.18)
Requires-Dist: pyarc2 (>=0.4.1)
Requires-Dist: pyqtgraph (>=0.13.0)
Requires-Dist: requests (>=2.20)
Requires-Dist: semver (>=2.0)
Requires-Dist: tomli (>=1.0)
Project-URL: Homepage, https://arc-instruments.co.uk
Project-URL: Repository, https://github.com/arc-instruments/arc2control
